mobile_detector
