Metadata-Version: 1.0
Name: django-mobile-detector
Version: 0.1.3
Summary: A small app to detect mobile browsers.
Home-page: https://github.com/madisona/django-mobile-detector
Author: Aaron Madison
Author-email: aaron.l.madison@gmail.com
License: UNKNOWN
Platform: UNKNOWN
Classifier: Development Status :: 3 - Alpha
Classifier: Environment :: Web Environment
Classifier: Framework :: Django
Classifier: Intended Audience :: Developers
Classifier: License :: OSI Approved :: BSD License
Classifier: Operating System :: OS Independent
Classifier: Programming Language :: Python
Classifier: Topic :: Software Development
Classifier: Topic :: Software Development :: Libraries :: Application Frameworks
